MLE_Trans/EncodeLabeler.py
MLE_Trans/__init__.py
MultiLabel_Transformer-0.3.dist-info/LICENSE
MultiLabel_Transformer-0.3.dist-info/METADATA
MultiLabel_Transformer-0.3.dist-info/WHEEL
MultiLabel_Transformer-0.3.dist-info/top_level.txt
MultiLabel_Transformer-0.3.dist-info/RECORD
