Metadata-Version: 2.1
Name: MultiLabel-Transformer
Version: 0.3
Summary: An Extended Transformer version of LabelEncoder that preprocesses more than one column in a dataset.
Home-page: https://github.com/Troublem1/MLE
Author: Emmanuel Siaw Darko
Author-email: immanuelsiawdarko@gmail.com
License: UNKNOWN
Platform: UNKNOWN
